setup.py
tinkerforge_util/__init__.py
tinkerforge_util/app_launcher.py
tinkerforge_util/changed_directory.py
tinkerforge_util/create_parent_module.py
tinkerforge_util/drop_stdin_buffer.py
tinkerforge_util/get_tf_printer_host.py
tinkerforge_util/specialize_template.py
tinkerforge_util/write_file_if_different.py
tinkerforge_util.egg-info/PKG-INFO
tinkerforge_util.egg-info/SOURCES.txt
tinkerforge_util.egg-info/dependency_links.txt
tinkerforge_util.egg-info/top_level.txt