Metadata-Version: 2.4
Name: tinkerforge_util
Version: 1.4.0
Summary: Python utilities for internal Tinkerforge usage
Home-page: https://www.tinkerforge.com
Author: Tinkerforge GmbH
Author-email: matthias@tinkerforge.com
License: LGPLv2+
Platform: Any
Dynamic: author
Dynamic: author-email
Dynamic: home-page
Dynamic: license
Dynamic: platform
Dynamic: summary
